cray/__init__.py
cray/config.py
cray/jobs.py
cray/s3.py
cray/tasks.py
cray/commands/__init__.py
cray/commands/cancel.py
cray/commands/jobs.py
cray/commands/logs.py
cray/commands/main.py
cray/commands/status.py
cray/commands/submit.py
cray/commands/tasks.py
Cray-0.0.10.dist-info/METADATA
Cray-0.0.10.dist-info/WHEEL
Cray-0.0.10.dist-info/entry_points.txt
Cray-0.0.10.dist-info/namespace_packages.txt
Cray-0.0.10.dist-info/top_level.txt
Cray-0.0.10.dist-info/RECORD
