Metadata-Version: 2.1
Name: Cray
Version: 0.0.10
Summary: CLI for interacting with the batch processing system
Home-page: UNKNOWN
Author: Dan Reid
Author-email: dan@senseye.io
License: UNKNOWN
Platform: Any
Classifier: Development Status :: 3 - Alpha
Classifier: Programming Language :: Python
Classifier: Programming Language :: Python :: 2
Classifier: Programming Language :: Python :: 2.7
Classifier: Programming Language :: Python :: 3
Classifier: Programming Language :: Python :: 3.2
Classifier: Intended Audience :: Developers
Classifier: Environment :: Console
Requires-Dist: cliff
Requires-Dist: boto3
